README.rst
setup.cfg
setup.py
cryptux/__init__.py
cryptux.egg-info/PKG-INFO
cryptux.egg-info/SOURCES.txt
cryptux.egg-info/dependency_links.txt
cryptux.egg-info/requires.txt
cryptux.egg-info/top_level.txt
cryptux/bitcoin/__init__.py
cryptux/bitcoin/account.py
cryptux/bitcoin/base58.py
cryptux/bitcoin/constants.py
cryptux/bitcoin/gen_addr.py
cryptux/bitcoin/hashes.py
cryptux/bitcoin/test_bitcoin_gen_addr.py
cryptux/bitcoin/wallet.py
cryptux/bitcoin/wif.py
tools/cryptux