Metadata-Version: 1.1
Name: cryptux
Version: 0.0.15
Summary: Simple wallet for Cryptocurrencies
Home-page: https://github.com/VISCHub/cryptux
Author: Viet Le
Author-email: vietlq85@gmail.com
License: UNKNOWN
Keywords: crypto hdw wallet bitcoin ether
Platform: UNKNOWN
Classifier: Development Status :: 3 - Alpha
Classifier: Environment :: Console
Classifier: Intended Audience :: Developers
Classifier: License :: OSI Approved :: Apache Software License
Classifier: Operating System :: OS Independent
Classifier: Programming Language :: Python
Classifier: Programming Language :: Python :: 2
Classifier: Programming Language :: Python :: 2.7
Classifier: Programming Language :: Python :: 3
Classifier: Programming Language :: Python :: 3.4
Classifier: Programming Language :: Python :: 3.5
Classifier: Programming Language :: Python :: 3.6
Classifier: Topic :: Software Development :: Libraries :: Python Modules
